HRM/__init__.py
HRM/hrm.py
HRM/hrm_with_act.py
hrm_pytorch-0.1.6.dist-info/METADATA
hrm_pytorch-0.1.6.dist-info/WHEEL
hrm_pytorch-0.1.6.dist-info/licenses/LICENSE
hrm_pytorch-0.1.6.dist-info/RECORD
