Metadata-Version: 2.4
Name: HRM-pytorch
Version: 0.1.6
Summary: The proposal from a Singaporean AGI company
Project-URL: Homepage, https://pypi.org/project/HRM-pytorch/
Project-URL: Repository, https://github.com/lucidrains/hrm
Author-email: Phil Wang <lucidrains@gmail.com>
License: MIT License
License-File: LICENSE
Keywords: adaptive computation time,artificial intelligence,deep learning,fast slow thinking
Classifier: Development Status :: 4 - Beta
Classifier: Intended Audience :: Developers
Classifier: License :: OSI Approved :: MIT License
Classifier: Programming Language :: Python :: 3.9
Classifier: Topic :: Scientific/Engineering :: Artificial Intelligence
Requires-Python: >=3.9
Requires-Dist: adam-atan2-pytorch
Requires-Dist: einops>=0.8.0
Requires-Dist: einx>=0.3.0
Requires-Dist: torch>=2.0
Requires-Dist: x-transformers>=2.5.0
Provides-Extra: examples
Provides-Extra: test
Requires-Dist: pytest; extra == 'test'
